{
    "code": 0,
    "message": "Success",
    "zpData": {
        "resCount": 450,
        "filterString": "",
        "lid": "24hGtVFPdZR",
        "hasMore": true,
        "jobList": [
            {
                "securityId": "oLUnrMT91Yuio-U1btrWIYKBlVtWY7jC9gQEJbQK0uSmDrH1Fyf6_X_O3oYbCi3y82ReHeUgW4LTPYAoVTyncfomN5e1c8mIScDl8MZ4idYNxfRRDWT5ixYUjpXZkz0tqpu3ZfbIET4c-Q~~",
                "bossAvatar": "https://img.bosszhipin.com/beijin/upload/avatar/20211125/607f1f3d68754fd0c1cbe12fd202b34a1240be9810c94171c996e2c17e49accbd222a8e658e12b5f_s.jpg",
                "bossCert": 3,
                "encryptBossId": "6ac1f2bc357a77d91nVy3Ni0EVU~",
                "bossName": "叶先生",
                "bossTitle": "招聘者",
                "goldHunter": 0,
                "bossOnline": false,
                "encryptJobId": "88244533fc9cb42f1Xd609S6FVJU",
                "expectId": 1197232932,
                "jobName": "爬虫工程师",
                "lid": "24hGtVFPdZR.search.91",
                "salaryDesc": "20-40K",
                "jobLabels": [
                    "经验不限",
                    "学历不限"
                ],
                "jobValidStatus": 1,
                "iconWord": "",
                "skills": [
                    "网络爬虫技术"
                ],
                "jobExperience": "经验不限",
                "daysPerWeekDesc": "",
                "leastMonthDesc": "",
                "jobDegree": "学历不限",
                "cityName": "北京",
                "areaDistrict": "朝阳区",
                "businessDistrict": "常营",
                "jobType": 0,
                "proxyJob": 0,
                "proxyType": 0,
                "anonymous": 0,
                "outland": 0,
                "optimal": 0,
                "iconFlagList": [],
                "itemId": 91,
                "city": 101010100,
                "isShield": 0,
                "atsDirectPost": false,
                "gps": {
                    "longitude": 116.582044,
                    "latitude": 39.926311
                },
                "afterNameIcons": [],
                "beforeNameIcons": [],
                "encryptBrandId": "e8f748a58728fc361XV63du7FFY~",
                "brandName": "灵光星河",
                "brandLogo": "https://img.bosszhipin.com/beijin/icon/894ce6fa7e58d64d57e7f22d2f3a9d18afa7fcceaa24b8ea28f56f1bb14732c0.png",
                "brandStageName": "",
                "brandIndustry": "大数据",
                "brandScaleName": "0-20人",
                "welfareList": [],
                "industry": 100005,
                "contact": false,
                "showTopPosition": false
            },
            {
                "securityId": "pNmcHW6X-FyhM-s13VjphN-Ehjqv2R2ykt0vGEUAcFgw2NsqMNqeqxbLPxKmfWPXgVR3978Ow5KEuu1Jd7ksgwZtpNmAnPxnHx3UyomYQUQqSna4nvq_tqzOYQIGsfwYEFAacud3fo-XmdY~",
                "bossAvatar": "https://img.bosszhipin.com/beijin/upload/avatar/20240312/607f1f3d68754fd05402eaf8bec5ff7a9ae3078b09a5c3ff3b0a52736f5b09eca87e8ce3c2508f3c_s.png.webp",
                "bossCert": 3,
                "encryptBossId": "8c14c3c9041d32630XB709u6GVFT",
                "bossName": "吴雨童",
                "bossTitle": "人力",
                "goldHunter": 0,
                "bossOnline": false,
                "encryptJobId": "5d588e4c1466e1371Hxz09S0F1BS",
                "expectId": 1197232932,
                "jobName": "高级爬虫工程师",
                "lid": "24hGtVFPdZR.search.92",
                "salaryDesc": "10-15K",
                "jobLabels": [
                    "经验不限",
                    "本科"
                ],
                "jobValidStatus": 1,
                "iconWord": "",
                "skills": [
                    "爬虫",
                    "JS逆向"
                ],
                "jobExperience": "经验不限",
                "daysPerWeekDesc": "",
                "leastMonthDesc": "",
                "jobDegree": "本科",
                "cityName": "北京",
                "areaDistrict": "朝阳区",
                "businessDistrict": "亚运村",
                "jobType": 0,
                "proxyJob": 0,
                "proxyType": 0,
                "anonymous": 0,
                "outland": 0,
                "optimal": 0,
                "iconFlagList": [],
                "itemId": 92,
                "city": 101010100,
                "isShield": 0,
                "atsDirectPost": false,
                "gps": {
                    "longitude": 116.390097,
                    "latitude": 39.980941
                },
                "afterNameIcons": [],
                "beforeNameIcons": [],
                "encryptBrandId": "095f599c5824e28e1Hd83t67FFs~",
                "brandName": "芯达数安",
                "brandLogo": "https://img.bosszhipin.com/beijin/icon/894ce6fa7e58d64d57e7f22d2f3a9d18afa7fcceaa24b8ea28f56f1bb14732c0.png",
                "brandStageName": "",
                "brandIndustry": "计算机软件",
                "brandScaleName": "0-20人",
                "welfareList": [],
                "industry": 100021,
                "contact": false,
                "showTopPosition": false
            },
            {
                "securityId": "AyC1vRFHdk_e5-y1l81w8kK9y0II6UvBgvKeunQ5I7A-lxZYit4JGdIxj7HC_G41JTG57Z1TvCuN8rVkGHfUoeq28V78VzuvqHgfa47LzgTUyXjDwgyb_gyJwBwil_O7QYLostdPL46znJo~",
                "bossAvatar": "https://img.bosszhipin.com/beijin/upload/avatar/20221009/607f1f3d68754fd016c0481cdff151a6201c1387fd2280fa5fe180ae0634fc66f499162e5298cdf7_s.jpg",
                "bossCert": 3,
                "encryptBossId": "c034857b8066b0371nR82N2-ElZV",
                "bossName": "程梓航",
                "bossTitle": "人事",
                "goldHunter": 0,
                "bossOnline": false,
                "encryptJobId": "e0d68d2669b6873803d909S-EFBU",
                "expectId": 1197232932,
                "jobName": "爬虫工程师",
                "lid": "24hGtVFPdZR.search.93",
                "salaryDesc": "10-15K",
                "jobLabels": [
                    "经验不限",
                    "本科"
                ],
                "jobValidStatus": 1,
                "iconWord": "",
                "skills": [
                    "爬虫",
                    "有解决问题能力"
                ],
                "jobExperience": "经验不限",
                "daysPerWeekDesc": "",
                "leastMonthDesc": "",
                "jobDegree": "本科",
                "cityName": "北京",
                "areaDistrict": "朝阳区",
                "businessDistrict": "国贸",
                "jobType": 0,
                "proxyJob": 0,
                "proxyType": 0,
                "anonymous": 0,
                "outland": 0,
                "optimal": 0,
                "iconFlagList": [],
                "itemId": 93,
                "city": 101010100,
                "isShield": 0,
                "atsDirectPost": false,
                "gps": {
                    "longitude": 116.469331,
                    "latitude": 39.903056
                },
                "afterNameIcons": [],
                "beforeNameIcons": [],
                "encryptBrandId": "7db663239f125cf71XV939y_FlM~",
                "brandName": "北京启辰金航资产管理",
                "brandLogo": "https://img.bosszhipin.com/beijin/icon/894ce6fa7e58d64d57e7f22d2f3a9d18afa7fcceaa24b8ea28f56f1bb14732c0.png",
                "brandStageName": "",
                "brandIndustry": "证券/期货",
                "brandScaleName": "20-99人",
                "welfareList": [],
                "industry": 100203,
                "contact": false,
                "showTopPosition": false
            },
            {
                "securityId": "2rmp3oTWkIDak-o1IHpWe9gnz0sPLp02BmWoabxD5z1JnkLHG6MDwnFF7OixUnKknUpTxY8BQb-Aovm5xmOtUT-Ik92TSM29-EVaRFfYdTd7bBNQUIKl02X9viglmqMM8QkxV6qb95XdAA~~",
                "bossAvatar": "https://img.bosszhipin.com/boss/avatar/avatar_6.png",
                "bossCert": 3,
                "encryptBossId": "c192021f8b85de6f1HZy09--EVQ~",
                "bossName": "马先生",
                "bossTitle": "CTO",
                "goldHunter": 0,
                "bossOnline": false,
                "encryptJobId": "7c4a4d974f13890d1nJ53t21EVNQ",
                "expectId": 1197232932,
                "jobName": "爬虫工程师",
                "lid": "24hGtVFPdZR.search.94",
                "salaryDesc": "11-22K·13薪",
                "jobLabels": [
                    "3-5年",
                    "学历不限"
                ],
                "jobValidStatus": 1,
                "iconWord": "",
                "skills": [
                    "网络爬虫技术"
                ],
                "jobExperience": "3-5年",
                "daysPerWeekDesc": "",
                "leastMonthDesc": "",
                "jobDegree": "学历不限",
                "cityName": "北京",
                "areaDistrict": "昌平区",
                "businessDistrict": "霍营",
                "jobType": 0,
                "proxyJob": 0,
                "proxyType": 0,
                "anonymous": 0,
                "outland": 0,
                "optimal": 0,
                "iconFlagList": [],
                "itemId": 94,
                "city": 101010100,
                "isShield": 0,
                "atsDirectPost": false,
                "gps": {
                    "longitude": 116.371273,
                    "latitude": 40.086114
                },
                "afterNameIcons": [],
                "beforeNameIcons": [],
                "encryptBrandId": "430ca4db65369b801nB43t-5GVs~",
                "brandName": "信查查有限公司",
                "brandLogo": "https://img.bosszhipin.com/beijin/upload/com/logo/20210226/24ecc667ab5900d4dcef90c321e6eb1e1f061b88c87a0df6b74790dd3a1ea00f.png",
                "brandStageName": "未融资",
                "brandIndustry": "企业服务",
                "brandScaleName": "100-499人",
                "welfareList": [
                    "生日会",
                    "零食下午茶",
                    "员工旅游",
                    "五险一金",
                    "住房补贴",
                    "入职周年庆",
                    "年终奖",
                    "节日福利",
                    "股票期权",
                    "带薪年假",
                    "五星级英雄宴",
                    "通讯补贴"
                ],
                "industry": 100015,
                "contact": false,
                "showTopPosition": false
            },
            {
                "securityId": "GVxdGkHn6Frmu-G1EWOGhbQ2NY-qsrCkDqp8XI4wmi1MHj1thxhD19D1bP-3qOAA3qsOPN0dhNkJFtWM6RwRu3uvwm4C3-sTZywENQV9QO5yIl_nQAFi92c2DZe1qyV2qMASZ0TloqUQH_8~",
                "bossAvatar": "https://img.bosszhipin.com/beijin/upload/avatar/20241002/607f1f3d68754fd0d5a1e70eae9b2740b32d48b8c3ea914115cf224249d81fbb4553fd449b7f0261_s.jpg.webp",
                "bossCert": 3,
                "encryptBossId": "1a778ca8b3390e0a0XNy39S9ElpS",
                "bossName": "李梦达",
                "bossTitle": "ceo",
                "goldHunter": 0,
                "bossOnline": false,
                "encryptJobId": "b2b54e04fb056c7703R_3ti6FVZX",
                "expectId": 1197232932,
                "jobName": "高级爬虫工程师",
                "lid": "24hGtVFPdZR.search.95",
                "salaryDesc": "800-1000元/天",
                "jobLabels": [
                    "3-5年",
                    "本科"
                ],
                "jobValidStatus": 1,
                "iconWord": "",
                "skills": [
                    "爬虫"
                ],
                "jobExperience": "3-5年",
                "daysPerWeekDesc": "",
                "leastMonthDesc": "",
                "jobDegree": "本科",
                "cityName": "北京",
                "areaDistrict": "朝阳区",
                "businessDistrict": "常营",
                "jobType": 6,
                "proxyJob": 0,
                "proxyType": 0,
                "anonymous": 0,
                "outland": 0,
                "optimal": 0,
                "iconFlagList": [],
                "itemId": 95,
                "city": 101010100,
                "isShield": 0,
                "atsDirectPost": false,
                "gps": {
                    "longitude": 116.587876,
                    "latitude": 39.944098
                },
                "afterNameIcons": [],
                "beforeNameIcons": [],
                "encryptBrandId": "8f8e3a170ac38f3a1HN83tu-FVA~",
                "brandName": "里斯比科技",
                "brandLogo": "https://img.bosszhipin.com/beijin/icon/894ce6fa7e58d64d57e7f22d2f3a9d18afa7fcceaa24b8ea28f56f1bb14732c0.png",
                "brandStageName": "",
                "brandIndustry": "人工智能",
                "brandScaleName": "0-20人",
                "welfareList": [],
                "industry": 100028,
                "contact": false,
                "showTopPosition": false
            },
            {
                "securityId": "-KMMJmnRxMsvw-J1XC7ZX_mzbZTo5JKgMq9kC1uppHp1-TdETAD0myo3eE2vcUlNwFeysgRlR-pYQc6Y7XaedVhXTy_xD7DzZEPNTuAL9HaKXpeVT25kMvhLLcVoudQdoyjVcTPzExB-LE2Q3CcUez_PbWE4kscyJRA-K0p2D82b",
                "bossAvatar": "https://img.bosszhipin.com/beijin/upload/avatar/20191126/3f6496e5c9c980d5ca39360652e3a6f4e8ee29547ca92b9ad6f04a04427f5d6f_s.jpg",
                "bossCert": 3,
                "encryptBossId": "bfc94ed89d555e6a0n193d-6Elc~",
                "bossName": "宁姜燕",
                "bossTitle": "HRBP",
                "goldHunter": 0,
                "bossOnline": true,
                "encryptJobId": "12c5b6818dedb6e81HR83dW9FlNY",
                "expectId": 1197232932,
                "jobName": "python爬虫开发工程师",
                "lid": "24hGtVFPdZR.search.96",
                "salaryDesc": "10-15K",
                "jobLabels": [
                    "1-3年",
                    "本科"
                ],
                "jobValidStatus": 1,
                "iconWord": "",
                "skills": [],
                "jobExperience": "1-3年",
                "daysPerWeekDesc": "",
                "leastMonthDesc": "",
                "jobDegree": "本科",
                "cityName": "北京",
                "areaDistrict": "海淀区",
                "businessDistrict": "清河",
                "jobType": 0,
                "proxyJob": 0,
                "proxyType": 0,
                "anonymous": 0,
                "outland": 0,
                "optimal": 0,
                "iconFlagList": [],
                "itemId": 96,
                "city": 101010100,
                "isShield": 0,
                "atsDirectPost": false,
                "gps": {
                    "longitude": 116.360618,
                    "latitude": 40.060656
                },
                "afterNameIcons": [],
                "beforeNameIcons": [],
                "encryptBrandId": "867dad38d96404220nJy2w~~",
                "brandName": "拓尔思",
                "brandLogo": "https://img2.bosszhipin.com/mcs/chatphoto/20151215/db58501456f9029afc98b3b708df74d22e46ab6e07ae8fe757ec1a0b955e5bda.gif",
                "brandStageName": "已上市",
                "brandIndustry": "互联网",
                "brandScaleName": "1000-9999人",
                "welfareList": [
                    "五险一金",
                    "带薪年假",
                    "定期体检",
                    "节日福利",
                    "补充医疗保险"
                ],
                "industry": 100020,
                "contact": false,
                "showTopPosition": false
            },
            {
                "securityId": "-5_kB4rg8sLMt-617ZEGGlVfNkexeBDYK4osJi21VafYB-Cxtg4QeYjbIRKBwQ_o_qSm9fy89TLHjD-oXz-OFD4hC6BVPw84xp43nXXhEa7-PnxFGfPMv1ZLvSWWElPuc3Akyhg3iyCaM5g~",
                "bossAvatar": "https://img.bosszhipin.com/beijin/upload/avatar/20240806/607f1f3d68754fd02d820007aaeddd08d1334c8b08615f944366167aa6eeb3530903693157e500ef_s.png.webp",
                "bossCert": 3,
                "encryptBossId": "3771b8a34e2be7070XN60tS5E1RV",
                "bossName": "赵蕾",
                "bossTitle": "人资经理",
                "goldHunter": 0,
                "bossOnline": false,
                "encryptJobId": "20f410ccf0e72ca403d72Nq9EFVQ",
                "expectId": 1197232932,
                "jobName": "爬虫Python工程师",
                "lid": "24hGtVFPdZR.search.97",
                "salaryDesc": "10-15K",
                "jobLabels": [
                    "3-5年",
                    "本科"
                ],
                "jobValidStatus": 1,
                "iconWord": "",
                "skills": [
                    "爬虫",
                    "Python",
                    "破解",
                    "航班",
                    "机票",
                    "航空公司",
                    "航司",
                    "票代"
                ],
                "jobExperience": "3-5年",
                "daysPerWeekDesc": "",
                "leastMonthDesc": "",
                "jobDegree": "本科",
                "cityName": "北京",
                "areaDistrict": "",
                "businessDistrict": "",
                "jobType": 0,
                "proxyJob": 0,
                "proxyType": 0,
                "anonymous": 0,
                "outland": 0,
                "optimal": 0,
                "iconFlagList": [],
                "itemId": 97,
                "city": 101010100,
                "isShield": 0,
                "atsDirectPost": false,
                "gps": {
                    "longitude": 116.350119,
                    "latitude": 39.762406
                },
                "afterNameIcons": [],
                "beforeNameIcons": [],
                "encryptBrandId": "5e07622d7280f0fa1nN92t29GFs~",
                "brandName": "易行慧通",
                "brandLogo": "https://img.bosszhipin.com/beijin/upload/com/workfeel/20210615/5d1da694cf505a4de130f596d209887937da7acde0b5832b55ea13bd6a3b9a5d.jpg",
                "brandStageName": "未融资",
                "brandIndustry": "其他专业服务",
                "brandScaleName": "20-99人",
                "welfareList": [
                    "交通补助",
                    "五险一金",
                    "节日福利",
                    "带薪年假",
                    "餐补",
                    "包吃",
                    "年终奖",
                    "通讯补贴"
                ],
                "industry": 100608,
                "contact": false,
                "showTopPosition": false
            },
            {
                "securityId": "pV_MbvzSJf7Iq-p1KJuYzHANS3vGwJJkk9FUML4frX5IOcdnt_3a0KSHoSA881dr0yZkHKMJ3EeDI3RszOX4EBiQZsfzU12XLnTllT4ANPtHNeIO_stuBzklL3CwCkq-0dR3qThBevW5hdqjiQwKDG2DAMni5p3FWmRWsnw8Uzim1qcwvpo~",
                "bossAvatar": "https://img.bosszhipin.com/boss/avatar/avatar_3.png",
                "bossCert": 3,
                "encryptBossId": "76a334b415d24bc30XJ839m6F1FV",
                "bossName": "李女士",
                "bossTitle": "人事经理",
                "goldHunter": 0,
                "bossOnline": true,
                "encryptJobId": "ec97808b5f1a77491HN63Nq-GFpT",
                "expectId": 1197232932,
                "jobName": "国际机票研发工程师（爬虫方向）",
                "lid": "24hGtVFPdZR.search.98",
                "salaryDesc": "20-30K",
                "jobLabels": [
                    "3-5年",
                    "本科"
                ],
                "jobValidStatus": 1,
                "iconWord": "",
                "skills": [
                    "反编译",
                    "高并发",
                    "APP逆向",
                    "网页抓取",
                    "985/211高校"
                ],
                "jobExperience": "3-5年",
                "daysPerWeekDesc": "",
                "leastMonthDesc": "",
                "jobDegree": "本科",
                "cityName": "北京",
                "areaDistrict": "朝阳区",
                "businessDistrict": "奥运村",
                "jobType": 0,
                "proxyJob": 0,
                "proxyType": 0,
                "anonymous": 0,
                "outland": 0,
                "optimal": 0,
                "iconFlagList": [],
                "itemId": 98,
                "city": 101010100,
                "isShield": 0,
                "atsDirectPost": false,
                "gps": {
                    "longitude": 116.43288,
                    "latitude": 40.048617
                },
                "afterNameIcons": [],
                "beforeNameIcons": [],
                "encryptBrandId": "a4a9a7215fcfec001HJ62tq6Elc~",
                "brandName": "北京汇游科技有限公司",
                "brandLogo": "https://img.bosszhipin.com/beijin/upload/com/workfeel/20241202/7bf6f160950405e94acbc0ffe6652e2e6fc09962fde22f3ebb89e6ce58bc22c9d7622349f3843233.png.webp",
                "brandStageName": "未融资",
                "brandIndustry": "互联网",
                "brandScaleName": "0-20人",
                "welfareList": [
                    "股票期权",
                    "绩效奖金",
                    "年终奖",
                    "定期体检",
                    "五险一金"
                ],
                "industry": 100020,
                "contact": false,
                "showTopPosition": false
            },
            {
                "securityId": "94KQzf87YqiMG-H1lgydkX6k1aKIvRuNcEdBR7cBx4hzRolxeLhNWxSEDTpB9HLnFDYO3h6PTE1rc39ZKey3lxgTmqrqaYeuwAzmtqqSXt6ozbJr4vbUiAWAeJ9X2MU7Ir5pv2la-phylNc~",
                "bossAvatar": "https://img.bosszhipin.com/boss/avatar/avatar_16.png",
                "bossCert": 3,
                "encryptBossId": "75714b79bf98166f0nFy0tu5F1JS",
                "bossName": "卢晓嘉",
                "bossTitle": "招聘者",
                "goldHunter": 0,
                "bossOnline": false,
                "encryptJobId": "348936409974c9e71HF83tq7EVtX",
                "expectId": 1197232932,
                "jobName": "高级爬虫工程师",
                "lid": "24hGtVFPdZR.search.99",
                "salaryDesc": "20-21K",
                "jobLabels": [
                    "3-5年",
                    "大专"
                ],
                "jobValidStatus": 1,
                "iconWord": "",
                "skills": [
                    "爬虫软件工程师"
                ],
                "jobExperience": "3-5年",
                "daysPerWeekDesc": "",
                "leastMonthDesc": "",
                "jobDegree": "大专",
                "cityName": "北京",
                "areaDistrict": "丰台区",
                "businessDistrict": "花乡",
                "jobType": 0,
                "proxyJob": 0,
                "proxyType": 0,
                "anonymous": 0,
                "outland": 0,
                "optimal": 0,
                "iconFlagList": [],
                "itemId": 99,
                "city": 101010100,
                "isShield": 0,
                "atsDirectPost": false,
                "gps": {
                    "longitude": 116.334373,
                    "latitude": 39.846684
                },
                "afterNameIcons": [],
                "beforeNameIcons": [],
                "encryptBrandId": "ffa79a78caa4c8c61Xdy29-5ElI~",
                "brandName": "北京四季畅游国际...",
                "brandLogo": "https://img.bosszhipin.com/beijin/icon/894ce6fa7e58d64d57e7f22d2f3a9d18afa7fcceaa24b8ea28f56f1bb14732c0.png",
                "brandStageName": "不需要融资",
                "brandIndustry": "旅游/景区",
                "brandScaleName": "20-99人",
                "welfareList": [
                    "绩效奖金",
                    "五险一金"
                ],
                "industry": 101103,
                "contact": false,
                "showTopPosition": false
            },
            {
                "securityId": "vOci-BklGqQzV-_1z42UXB8gBReb0WAkY08p-Q4zyVFRbLVfN0wEPJ4IhyvHaX2duH8GLt5Bdc_RyLRShwRIVSeyM0N4Vp3RlMMcDfGBHa6SKbE1PVAOrnZRYPaMbIZqckZ4rMEaF6g~",
                "bossAvatar": "https://img.bosszhipin.com/boss/avatar/avatar_11.png",
                "bossCert": 3,
                "encryptBossId": "3d55193d994116b41HV-3d64FVQ~",
                "bossName": "邱莎莎",
                "bossTitle": "hrbp",
                "goldHunter": 0,
                "bossOnline": false,
                "encryptJobId": "345c43b18707ba5a1H192t27ElFR",
                "expectId": 1197232932,
                "jobName": "python爬虫工程师",
                "lid": "24hGtVFPdZR.search.100",
                "salaryDesc": "11-22K",
                "jobLabels": [
                    "3-5年",
                    "大专"
                ],
                "jobValidStatus": 1,
                "iconWord": "",
                "skills": [
                    "Python",
                    "Java",
                    "Scrapy",
                    "MySQL",
                    "爬虫经验",
                    "分布式经验"
                ],
                "jobExperience": "3-5年",
                "daysPerWeekDesc": "",
                "leastMonthDesc": "",
                "jobDegree": "大专",
                "cityName": "北京",
                "areaDistrict": "朝阳区",
                "businessDistrict": "朝阳门",
                "jobType": 0,
                "proxyJob": 0,
                "proxyType": 0,
                "anonymous": 0,
                "outland": 0,
                "optimal": 0,
                "iconFlagList": [],
                "itemId": 100,
                "city": 101010100,
                "isShield": 0,
                "atsDirectPost": false,
                "gps": {
                    "longitude": 116.440779,
                    "latitude": 39.9282
                },
                "afterNameIcons": [],
                "beforeNameIcons": [],
                "encryptBrandId": "a8328398dad1ce021nx63tS5",
                "brandName": "北京保盛航空",
                "brandLogo": "https://img.bosszhipin.com/beijin/mcs/chatphoto/20170809/70f4199d68a3af3ddbe7ea129871d56c5cada7d5cf658e27cce1d9a050685783.jpg",
                "brandStageName": "不需要融资",
                "brandIndustry": "生活服务(O2O)",
                "brandScaleName": "500-999人",
                "welfareList": [
                    "夜班补助",
                    "节假日加班费",
                    "五险一金",
                    "法定节假日三薪",
                    "加班补助",
                    "底薪加提成",
                    "带薪年假",
                    "保底工资",
                    "绩效奖金"
                ],
                "industry": 100007,
                "contact": false,
                "showTopPosition": false
            },
            {
                "securityId": "Okt1zpth2NPI0-f1q7AJa3XbVkJxuWzvrY5oxlePsp-WxoL7fD4oV0JMXX9GllPoGvNW1MfvgLWxuAWBa_KSFqdYZoh1vF9HaiePc7rEsb2IBaXa1e7cOvBrKgSs1j7EZ-rSCYIoWLjlKw~~",
                "bossAvatar": "https://img.bosszhipin.com/beijin/mcs/useravatar/20180424/b2d5e14f61e67fc38e9b7c0c9207e9661395727edc0f172087934bef13b0cf34_s.jpg",
                "bossCert": 3,
                "encryptBossId": "3f865972ad2c52ee1nZy29m0FFM~",
                "bossName": "张女士",
                "bossTitle": "HR",
                "goldHunter": 0,
                "bossOnline": false,
                "encryptJobId": "0698a5ba5bb12fb103d82t6-EFFZ",
                "expectId": 1197232932,
                "jobName": "高级爬虫工程师",
                "lid": "24hGtVFPdZR.search.101",
                "salaryDesc": "25-50K·15薪",
                "jobLabels": [
                    "3-5年",
                    "本科"
                ],
                "jobValidStatus": 1,
                "iconWord": "",
                "skills": [],
                "jobExperience": "3-5年",
                "daysPerWeekDesc": "",
                "leastMonthDesc": "",
                "jobDegree": "本科",
                "cityName": "北京",
                "areaDistrict": "海淀区",
                "businessDistrict": "学院路",
                "jobType": 0,
                "proxyJob": 0,
                "proxyType": 0,
                "anonymous": 0,
                "outland": 0,
                "optimal": 0,
                "iconFlagList": [],
                "itemId": 101,
                "city": 101010100,
                "isShield": 0,
                "atsDirectPost": false,
                "gps": {
                    "longitude": 116.339376,
                    "latitude": 39.991919
                },
                "afterNameIcons": [],
                "beforeNameIcons": [],
                "encryptBrandId": "6bc632935686edec1HJy3924F1I~",
                "brandName": "SandAI",
                "brandLogo": "https://img.bosszhipin.com/beijin/upload/admin/20241009/7a57a5a743894a0e61db0c9f94e55da3789b92c168491f5575a8c6cfd5eed090fc41aa91be88d106.png.webp",
                "brandStageName": "A轮",
                "brandIndustry": "人工智能",
                "brandScaleName": "20-99人",
                "welfareList": [
                    "免费班车",
                    "带薪年假",
                    "五险一金",
                    "年终奖",
                    "零食下午茶",
                    "股票期权",
                    "生日福利",
                    "交通补助",
                    "节假日加班费"
                ],
                "industry": 100028,
                "contact": false,
                "showTopPosition": false
            },
            {
                "securityId": "_9rrjD5fmhJA8-114kHf-8tCcv_fDPTZk4mSMWQbPtWtsObJmZAxB2W7jJGKeDpvUEza4SrzMFonAfWm866Q_u9toO-h5CpRV6r45BZTty758BzMi-nyfCsNx5gWwimzyLap2LVCN2i9JA~~",
                "bossAvatar": "https://img.bosszhipin.com/beijin/upload/avatar/20210429/3ee4fa31ed0739ece9386e0921488c4486302a2b811f987b621db9e895c6f2e6_s.png",
                "bossCert": 3,
                "encryptBossId": "ad2d4ed3f91e154a03Z63Nm5FFM~",
                "bossName": "王女士",
                "bossTitle": "人事主管",
                "goldHunter": 0,
                "bossOnline": false,
                "encryptJobId": "eab0923e56114ede03Z-3dq1FVNR",
                "expectId": 1197232932,
                "jobName": "python爬虫开发工程师",
                "lid": "24hGtVFPdZR.search.102",
                "salaryDesc": "8-12K",
                "jobLabels": [
                    "5-10年",
                    "大专"
                ],
                "jobValidStatus": 1,
                "iconWord": "",
                "skills": [
                    "python",
                    "爬虫",
                    "Java",
                    "spring cloud",
                    "spring boot",
                    "数据抓取",
                    "数据分析"
                ],
                "jobExperience": "5-10年",
                "daysPerWeekDesc": "",
                "leastMonthDesc": "",
                "jobDegree": "大专",
                "cityName": "北京",
                "areaDistrict": "大兴区",
                "businessDistrict": "亦庄",
                "jobType": 0,
                "proxyJob": 0,
                "proxyType": 0,
                "anonymous": 0,
                "outland": 0,
                "optimal": 0,
                "iconFlagList": [],
                "itemId": 102,
                "city": 101010100,
                "isShield": 0,
                "atsDirectPost": false,
                "gps": {
                    "longitude": 116.483989,
                    "latitude": 39.808162
                },
                "afterNameIcons": [],
                "beforeNameIcons": [],
                "encryptBrandId": "4ba1c1a506f1b2961XN-2N28F1c~",
                "brandName": "婕恩婕",
                "brandLogo": "https://img.bosszhipin.com/beijin/icon/894ce6fa7e58d64d57e7f22d2f3a9d18afa7fcceaa24b8ea28f56f1bb14732c0.png",
                "brandStageName": "",
                "brandIndustry": "互联网",
                "brandScaleName": "20-99人",
                "welfareList": [],
                "industry": 100020,
                "contact": false,
                "showTopPosition": false
            },
            {
                "securityId": "MCPurAI43EEuQ-n1paBuzMuO3LoxbhipfSuMLeZ1yZGUWrxvpjBCtviKoL2O1qYlExLJSuvyxT3Ot-xMYyW5ikXB0iZj2CmmGnyOCEZt2LaukFQYC841xu6h7yDxIFpfYm9PkQJeGtolfkg~",
                "bossAvatar": "https://img.bosszhipin.com/beijin/upload/avatar/20220802/607f1f3d68754fd03e6664ba4c2fbf9890d8af6efa25e357d17a2b82a798e4898940f388a67fd0cf_s.jpg",
                "bossCert": 3,
                "encryptBossId": "87267f6c8b2930c70nF539-_GVpQ",
                "bossName": "杨雪艳",
                "bossTitle": "猎头顾问",
                "goldHunter": 1,
                "bossOnline": false,
                "encryptJobId": "67dfc2cf25e2bd0003Z_3Ny6FVdU",
                "expectId": 1197232932,
                "jobName": "爬虫工程师",
                "lid": "24hGtVFPdZR.search.103",
                "salaryDesc": "20-30K",
                "jobLabels": [
                    "经验不限",
                    "学历不限"
                ],
                "jobValidStatus": 1,
                "iconWord": "",
                "skills": [
                    "高考志愿填报",
                    "高考数据",
                    "高校网站",
                    "教育局官网数据"
                ],
                "jobExperience": "经验不限",
                "daysPerWeekDesc": "",
                "leastMonthDesc": "",
                "jobDegree": "学历不限",
                "cityName": "北京",
                "areaDistrict": "",
                "businessDistrict": "",
                "jobType": 0,
                "proxyJob": 1,
                "proxyType": 1,
                "anonymous": 20,
                "outland": 0,
                "optimal": 0,
                "iconFlagList": [
                    8
                ],
                "itemId": 103,
                "city": 101010100,
                "isShield": 0,
                "atsDirectPost": false,
                "gps": {
                    "longitude": 116.288301,
                    "latitude": 39.958603
                },
                "afterNameIcons": [],
                "beforeNameIcons": [
                    "https://img.bosszhipin.com/static/file/2022/cy4fi6cada1655206055291.png"
                ],
                "encryptBrandId": "",
                "brandName": "某互联网公司",
                "brandLogo": "https://img.bosszhipin.com/beijin/app/mobile/n-af8dd288f86448d9eaaf3a4b0fd60b27.png",
                "brandStageName": "不需要融资",
                "brandIndustry": "互联网",
                "brandScaleName": "20-99人",
                "welfareList": [
                    "五险一金",
                    "团建聚餐",
                    "带薪年假",
                    "年终奖",
                    "零食下午茶"
                ],
                "industry": 100020,
                "contact": false,
                "showTopPosition": false
            },
            {
                "securityId": "gOMNacYQ3K2x--F1KEzkhxqGzPa_W2hX6WY3bQ1d07k2uEUs8PNH5RmCCG2qcbIF6AImFUvejDBVCHCr53P0nJSD_LJ1CIqtc7HTMZ4ZfpE9H0Akg_sMo2NasH8FFWHj6Zegnl6j7i5MeaI~",
                "bossAvatar": "https://img.bosszhipin.com/beijin/upload/avatar/20250224/607f1f3d68754fd0cb81a97140e2cc1ed4ba52b52e641a15697c6f416605285591a902d4e505afc0_s.jpg.webp",
                "bossCert": 3,
                "encryptBossId": "4d9c9ffbd7b05add0Xd53ti7EVtQ",
                "bossName": "周女士",
                "bossTitle": "产品运营经理",
                "goldHunter": 0,
                "bossOnline": false,
                "encryptJobId": "ef16ef556da6724903Z43960E1VV",
                "expectId": 1197232932,
                "jobName": "高级逆向爬虫技术顾问",
                "lid": "24hGtVFPdZR.search.104",
                "salaryDesc": "150-200元/时",
                "jobLabels": [
                    "3-5年",
                    "学历不限"
                ],
                "jobValidStatus": 1,
                "iconWord": "",
                "skills": [
                    "爬虫",
                    "逆向",
                    "Python"
                ],
                "jobExperience": "3-5年",
                "daysPerWeekDesc": "",
                "leastMonthDesc": "",
                "jobDegree": "学历不限",
                "cityName": "北京",
                "areaDistrict": "通州区",
                "businessDistrict": "果园",
                "jobType": 6,
                "proxyJob": 0,
                "proxyType": 0,
                "anonymous": 0,
                "outland": 0,
                "optimal": 0,
                "iconFlagList": [],
                "itemId": 104,
                "city": 101010100,
                "isShield": 0,
                "atsDirectPost": false,
                "gps": {
                    "longitude": 116.661511,
                    "latitude": 39.875116
                },
                "afterNameIcons": [],
                "beforeNameIcons": [],
                "encryptBrandId": "a7702f6fe391475b1HZ73N6-EVM~",
                "brandName": "探数汇云",
                "brandLogo": "https://img.bosszhipin.com/beijin/upload/com/workfeel/20231227/7bf6f160950405e995745698d41e49df524c3cb7992a093c578709911653514a7d30c6649ea1d30a.png.webp",
                "brandStageName": "未融资",
                "brandIndustry": "大数据",
                "brandScaleName": "20-99人",
                "welfareList": [
                    "绩效奖金",
                    "底薪加提成",
                    "员工旅游",
                    "包吃",
                    "团建聚餐"
                ],
                "industry": 100005,
                "contact": false,
                "showTopPosition": false
            },
            {
                "securityId": "20yHJaBq8c-eO-h1m1ZD3v1QyzVvUPcO8ssWaftzXe1V9jBtqcXan98D0zcDfazgbHGnx9QR5vVgizOyhY6WX5ho43Ivqj2agZZLPCKNmuSXRJVqKMjTJXerL6lFf5S5CBzFvElYqr7SuJZxRa-i8UPQIWoqUx7hhUF8jaDgg65FtNTRLA~~",
                "bossAvatar": "https://img.bosszhipin.com/beijin/upload/avatar/20240731/607f1f3d68754fd068e1e5f0125059f3fedb7a6b94235bf9d05335dd5b70397c236072e35779d51a_s.jpg.webp",
                "bossCert": 3,
                "encryptBossId": "5a824765db2f13ba0nV52tS_FlJX",
                "bossName": "李女士",
                "bossTitle": "招聘专员",
                "goldHunter": 0,
                "bossOnline": true,
                "encryptJobId": "1747ed43ee6a7f321Hx80ti4GVpU",
                "expectId": 1197232932,
                "jobName": "爬虫工程师",
                "lid": "24hGtVFPdZR.search.105",
                "salaryDesc": "20-40K",
                "jobLabels": [
                    "3-5年",
                    "本科"
                ],
                "jobValidStatus": 1,
                "iconWord": "",
                "skills": [
                    "爬虫",
                    "Java",
                    "python",
                    "逆向",
                    "数据爬取"
                ],
                "jobExperience": "3-5年",
                "daysPerWeekDesc": "",
                "leastMonthDesc": "",
                "jobDegree": "本科",
                "cityName": "北京",
                "areaDistrict": "海淀区",
                "businessDistrict": "上地",
                "jobType": 0,
                "proxyJob": 0,
                "proxyType": 0,
                "anonymous": 0,
                "outland": 0,
                "optimal": 0,
                "iconFlagList": [],
                "itemId": 105,
                "city": 101010100,
                "isShield": 0,
                "atsDirectPost": false,
                "gps": {
                    "longitude": 116.287572,
                    "latitude": 40.046677
                },
                "afterNameIcons": [],
                "beforeNameIcons": [],
                "encryptBrandId": "9c28b6a026eb7f401HVy3di5FA~~",
                "brandName": "Flow++",
                "brandLogo": "https://img.bosszhipin.com/beijin/mcs/chatphoto/20181213/fb6704d5ab37a74431563b2dbd1b3acdcfcd208495d565ef66e7dff9f98764da.jpg",
                "brandStageName": "B轮",
                "brandIndustry": "大数据",
                "brandScaleName": "100-499人",
                "welfareList": [
                    "生日福利",
                    "定期体检",
                    "五险一金",
                    "股票期权",
                    "绩效奖金",
                    "团建聚餐",
                    "年终奖",
                    "节日福利",
                    "零食下午茶",
                    "带薪年假",
                    "意外险",
                    "补充医疗保险",
                    "员工旅游"
                ],
                "industry": 100005,
                "contact": false,
                "showTopPosition": false
            }
        ],
        "totalCount": 300,
        "brandCard": null
    }
}